{
  "v": "5.4.2",
  "fr": 29.9700012207031,
  "ip": 0,
  "op": 179.000007290819,
  "w": 100,
  "h": 100,
  "nm": "Comp 1",
  "ddd": 0,
  "assets": [],
  "layers": [
    {
      "ddd": 0,
      "ind": 1,
      "ty": 4,
      "nm": "icon-spinner Outlines",
      "sr": 1,
      "ks": {
        "o": {
          "a": 1,
          "k": [
            {
              "i": { "x": [0.833], "y": [0.833] },
              "o": { "x": [0.167], "y": [0.167] },
              "n": ["0p833_0p833_0p167_0p167"],
              "t": 0,
              "s": [0],
              "e": [100]
            },
            {
              "i": { "x": [0.833], "y": [0.833] },
              "o": { "x": [0.167], "y": [0.167] },
              "n": ["0p833_0p833_0p167_0p167"],
              "t": 28,
              "s": [100],
              "e": [0]
            },
            { "t": 60.0000024438501 }
          ],
          "ix": 11
        },
        "r": { "a": 0, "k": 21, "ix": 10 },
        "p": { "a": 0, "k": [49.75, 49.5, 0], "ix": 2 },
        "a": { "a": 0, "k": [167.936, 167.698, 0], "ix": 1 },
        "s": { "a": 0, "k": [29.283, 28.84, 100], "ix": 6 }
      },
      "ao": 0,
      "shapes": [
        {
          "ty": "gr",
          "it": [
            {
              "ind": 0,
              "ty": "sh",
              "ix": 1,
              "ks": {
                "a": 0,
                "k": {
                  "i": [
                    [0, 0],
                    [1.771, -1.743],
                    [0, -3.111],
                    [0, 0],
                    [20.698, -17.387],
                    [0, 0],
                    [1.529, 0.702],
                    [1.647, 0.06],
                    [1.529, -0.595],
                    [1.058, -1.148],
                    [0.588, -1.512],
                    [0, -1.624],
                    [-0.706, -1.465],
                    [-1.176, -1.062],
                    [0, 0],
                    [2.352, -26.884],
                    [0, 0],
                    [2.235, -2.201],
                    [0, -3.111],
                    [-2.117, -2.199],
                    [-3.176, 0],
                    [0, 0],
                    [-17.405, -20.641],
                    [0, 0],
                    [0.706, -1.466],
                    [0.118, -1.625],
                    [-0.588, -1.512],
                    [-1.177, -1.15],
                    [-1.529, -0.593],
                    [-1.528, 0.058],
                    [-1.411, 0.704],
                    [-1.058, 1.23],
                    [0, 0],
                    [-26.813, -2.36],
                    [0, 0],
                    [-2.117, -2.2],
                    [-3.058, 0],
                    [-2.235, 2.199],
                    [0, 3.112],
                    [0, 0],
                    [-20.697, 17.386],
                    [0, 0],
                    [-3.057, 0],
                    [-2.235, 2.141],
                    [0, 3.109],
                    [2.117, 2.237],
                    [0, 0],
                    [-2.352, 26.884],
                    [0, 0],
                    [-2.234, 2.201],
                    [0, 3.112],
                    [2.116, 2.199],
                    [3.175, 0],
                    [0, 0],
                    [17.405, 20.64],
                    [0, 0],
                    [0, 3.103],
                    [2.117, 2.247],
                    [3.175, 0],
                    [2.234, -2.161],
                    [0, 0],
                    [26.812, 2.359],
                    [0, 0],
                    [2.116, 2.2],
                    [2.394, 0.398]
                  ],
                  "o": [
                    [-2.394, 0.398],
                    [-2.117, 2.2],
                    [0, 0],
                    [-26.813, 2.359],
                    [0, 0],
                    [-1.058, -1.229],
                    [-1.411, -0.704],
                    [-1.528, -0.058],
                    [-1.529, 0.594],
                    [-1.177, 1.149],
                    [-0.588, 1.511],
                    [0.118, 1.623],
                    [0.706, 1.465],
                    [0, 0],
                    [-17.405, 20.64],
                    [0, 0],
                    [-3.176, 0],
                    [-2.117, 2.199],
                    [0, 3.112],
                    [2.235, 2.201],
                    [0, 0],
                    [2.352, 26.884],
                    [0, 0],
                    [-1.176, 1.063],
                    [-0.706, 1.464],
                    [0, 1.624],
                    [0.588, 1.511],
                    [1.058, 1.148],
                    [1.529, 0.595],
                    [1.647, -0.06],
                    [1.529, -0.702],
                    [0, 0],
                    [20.698, 17.386],
                    [0, 0],
                    [0, 3.112],
                    [2.235, 2.199],
                    [3.058, 0],
                    [2.116, -2.2],
                    [0, 0],
                    [26.812, -2.36],
                    [0, 0],
                    [2.234, 2.141],
                    [3.175, 0],
                    [2.117, -2.237],
                    [0, -3.111],
                    [0, 0],
                    [17.405, -20.641],
                    [0, 0],
                    [3.175, 0],
                    [2.116, -2.199],
                    [0, -3.111],
                    [-2.234, -2.201],
                    [0, 0],
                    [-2.352, -26.884],
                    [0, 0],
                    [2.117, -2.248],
                    [0, -3.103],
                    [-2.235, -2.161],
                    [-3.057, 0],
                    [0, 0],
                    [-20.697, -17.387],
                    [0, 0],
                    [0, -3.111],
                    [-1.771, -1.743],
                    [0, 0]
                  ],
                  "v": [
                    [-1.898, -167.5],
                    [-8.35, -164.222],
                    [-11.76, -155.928],
                    [-11.76, -131.849],
                    [-84.789, -101.508],
                    [-101.841, -118.619],
                    [-105.722, -121.548],
                    [-110.426, -122.705],
                    [-115.13, -121.893],
                    [-119.128, -119.251],
                    [-121.833, -115.216],
                    [-122.656, -110.462],
                    [-121.48, -105.78],
                    [-118.54, -101.949],
                    [-101.37, -84.838],
                    [-131.711, -11.81],
                    [-155.818, -11.81],
                    [-164.169, -8.373],
                    [-167.579, -0.079],
                    [-164.169, 8.215],
                    [-155.818, 11.652],
                    [-131.711, 11.652],
                    [-101.37, 84.681],
                    [-118.54, 101.791],
                    [-121.48, 105.623],
                    [-122.656, 110.305],
                    [-121.833, 115.059],
                    [-119.128, 119.093],
                    [-115.13, 121.735],
                    [-110.426, 122.547],
                    [-105.722, 121.39],
                    [-101.841, 118.461],
                    [-84.789, 101.351],
                    [-11.76, 131.692],
                    [-11.76, 155.769],
                    [-8.35, 164.064],
                    [0, 167.5],
                    [8.35, 164.064],
                    [11.76, 155.769],
                    [11.76, 131.692],
                    [84.789, 101.351],
                    [101.841, 118.461],
                    [110.19, 121.796],
                    [118.54, 118.461],
                    [121.95, 110.127],
                    [118.54, 101.791],
                    [101.37, 84.681],
                    [131.711, 11.652],
                    [155.819, 11.652],
                    [164.169, 8.215],
                    [167.579, -0.079],
                    [164.169, -8.373],
                    [155.819, -11.81],
                    [131.711, -11.81],
                    [101.37, -84.838],
                    [118.54, -101.949],
                    [121.833, -110.284],
                    [118.54, -118.619],
                    [110.19, -121.988],
                    [101.841, -118.619],
                    [84.789, -101.508],
                    [11.76, -131.849],
                    [11.76, -155.928],
                    [8.35, -164.222],
                    [1.898, -167.5]
                  ],
                  "c": true
                },
                "ix": 2
              },
              "nm": "Path 1",
              "mn": "ADBE Vector Shape - Group",
              "hd": false
            },
            {
              "ind": 1,
              "ty": "sh",
              "ix": 2,
              "ks": {
                "a": 0,
                "k": {
                  "i": [
                    [0, 0],
                    [-15.994, -13.202],
                    [0, 0],
                    [3.175, 0.911],
                    [0, 0]
                  ],
                  "o": [
                    [20.58, 2.096],
                    [0, 0],
                    [-2.705, -1.609],
                    [0, 0],
                    [0, 0]
                  ],
                  "v": [
                    [11.76, -108.211],
                    [67.973, -84.75],
                    [21.639, -38.446],
                    [12.818, -42.239],
                    [11.878, -42.239]
                  ],
                  "c": true
                },
                "ix": 2
              },
              "nm": "Path 2",
              "mn": "ADBE Vector Shape - Group",
              "hd": false
            },
            {
              "ind": 2,
              "ty": "sh",
              "ix": 3,
              "ks": {
                "a": 0,
                "k": {
                  "i": [
                    [0, 0],
                    [-20.579, 2.087],
                    [0, 0],
                    [0, 0],
                    [2.823, -1.609]
                  ],
                  "o": [
                    [16.111, -12.992],
                    [0, 0],
                    [0, 0],
                    [-3.058, 0.911],
                    [0, 0]
                  ],
                  "v": [
                    [-67.972, -85.103],
                    [-11.76, -108.211],
                    [-11.76, -42.503],
                    [-12.701, -42.503],
                    [-21.521, -38.711]
                  ],
                  "c": true
                },
                "ix": 2
              },
              "nm": "Path 3",
              "mn": "ADBE Vector Shape - Group",
              "hd": false
            },
            {
              "ind": 3,
              "ty": "sh",
              "ix": 4,
              "ks": {
                "a": 0,
                "k": {
                  "i": [
                    [-13.171, 15.981],
                    [0, 0],
                    [0.942, -3.088],
                    [0, 0],
                    [0, 0]
                  ],
                  "o": [
                    [0, 0],
                    [-1.647, 2.768],
                    [0, 0],
                    [0, 0],
                    [2.234, -20.6]
                  ],
                  "v": [
                    [-84.672, -68.08],
                    [-38.337, -21.776],
                    [-42.219, -12.956],
                    [-42.219, -11.986],
                    [-108.191, -11.986]
                  ],
                  "c": true
                },
                "ix": 2
              },
              "nm": "Path 4",
              "mn": "ADBE Vector Shape - Group",
              "hd": false
            },
            {
              "ind": 4,
              "ty": "sh",
              "ix": 5,
              "ks": {
                "a": 0,
                "k": {
                  "i": [
                    [0, 0],
                    [0, 0],
                    [1.647, 2.778],
                    [0, 0],
                    [-2.118, -20.663]
                  ],
                  "o": [
                    [0, 0],
                    [-0.94, -3.08],
                    [0, 0],
                    [13.172, 16.106],
                    [0, 0]
                  ],
                  "v": [
                    [42.453, -11.457],
                    [42.453, -12.427],
                    [38.572, -21.246],
                    [85.024, -67.639],
                    [108.427, -11.281]
                  ],
                  "c": true
                },
                "ix": 2
              },
              "nm": "Path 5",
              "mn": "ADBE Vector Shape - Group",
              "hd": false
            },
            {
              "ind": 5,
              "ty": "sh",
              "ix": 6,
              "ks": {
                "a": 0,
                "k": {
                  "i": [
                    [1.235, 0.235],
                    [2.47, 1.701],
                    [1.411, 2.029],
                    [0.47, 2.919],
                    [-0.588, 2.388],
                    [-1.646, 2.425],
                    [-1.999, 1.411],
                    [-2.94, 0.506],
                    [-2.469, -0.47],
                    [-2.47, -1.702],
                    [-1.412, -2.03],
                    [-0.471, -2.919],
                    [0.587, -2.386],
                    [1.646, -2.425],
                    [1.999, -1.411],
                    [2.941, -0.611],
                    [0, 0],
                    [1.205, 0]
                  ],
                  "o": [
                    [-2.94, -0.506],
                    [-1.999, -1.411],
                    [-1.646, -2.425],
                    [-0.588, -2.386],
                    [0.47, -2.919],
                    [1.411, -2.03],
                    [2.47, -1.702],
                    [2.47, -0.47],
                    [2.941, 0.506],
                    [1.999, 1.411],
                    [1.646, 2.425],
                    [0.587, 2.388],
                    [-0.471, 2.919],
                    [-1.412, 2.029],
                    [-2.47, 1.826],
                    [0, 0],
                    [-1.235, 0.235],
                    [-1.205, 0]
                  ],
                  "v": [
                    [-3.646, 19.854],
                    [-11.76, 16.503],
                    [-16.934, 11.299],
                    [-20.227, 3.184],
                    [-20.227, -4.048],
                    [-16.934, -12.162],
                    [-11.76, -17.366],
                    [-3.646, -20.718],
                    [3.645, -20.718],
                    [11.76, -17.366],
                    [16.935, -12.162],
                    [20.228, -4.048],
                    [20.228, 3.184],
                    [16.935, 11.299],
                    [11.76, 16.503],
                    [3.645, 20.207],
                    [3.645, 19.854],
                    [0, 20.206]
                  ],
                  "c": true
                },
                "ix": 2
              },
              "nm": "Path 6",
              "mn": "ADBE Vector Shape - Group",
              "hd": false
            },
            {
              "ind": 6,
              "ty": "sh",
              "ix": 7,
              "ks": {
                "a": 0,
                "k": {
                  "i": [
                    [2.234, 20.45],
                    [0, 0],
                    [0, 0],
                    [0, 0],
                    [-1.646, -2.779],
                    [0, 0]
                  ],
                  "o": [
                    [0, 0],
                    [0, 0],
                    [0, 0],
                    [0.94, 3.08],
                    [0, 0],
                    [-12.936, -15.989]
                  ],
                  "v": [
                    [-108.191, 11.652],
                    [-108.191, 11.299],
                    [-42.453, 11.299],
                    [-42.453, 12.269],
                    [-38.573, 21.089],
                    [-85.024, 67.481]
                  ],
                  "c": true
                },
                "ix": 2
              },
              "nm": "Path 7",
              "mn": "ADBE Vector Shape - Group",
              "hd": false
            },
            {
              "ind": 7,
              "ty": "sh",
              "ix": 8,
              "ks": {
                "a": 0,
                "k": {
                  "i": [
                    [0, 0],
                    [-0.94, 3.08],
                    [0, 0],
                    [0, 0],
                    [13.053, -16.014]
                  ],
                  "o": [
                    [1.647, -2.779],
                    [0, 0],
                    [0, 0],
                    [-2, 20.57],
                    [0, 0]
                  ],
                  "v": [
                    [38.337, 21.618],
                    [42.217, 12.798],
                    [42.217, 11.828],
                    [107.839, 11.828],
                    [84.672, 67.923]
                  ],
                  "c": true
                },
                "ix": 2
              },
              "nm": "Path 8",
              "mn": "ADBE Vector Shape - Group",
              "hd": false
            },
            {
              "ind": 8,
              "ty": "sh",
              "ix": 9,
              "ks": {
                "a": 0,
                "k": {
                  "i": [
                    [15.993, 13.201],
                    [0, 0],
                    [-3.176, -0.888],
                    [0, 0],
                    [0, 0]
                  ],
                  "o": [
                    [0, 0],
                    [2.704, 1.63],
                    [0, 0],
                    [0, 0],
                    [-20.579, -2.096]
                  ],
                  "v": [
                    [-67.972, 84.593],
                    [-21.638, 38.288],
                    [-12.818, 42.08],
                    [-11.877, 42.08],
                    [-11.76, 108.054]
                  ],
                  "c": true
                },
                "ix": 2
              },
              "nm": "Path 9",
              "mn": "ADBE Vector Shape - Group",
              "hd": false
            },
            {
              "ind": 9,
              "ty": "sh",
              "ix": 10,
              "ks": {
                "a": 0,
                "k": {
                  "i": [
                    [0, 0],
                    [0, 0],
                    [-2.822, 1.609],
                    [0, 0],
                    [20.58, -2.088]
                  ],
                  "o": [
                    [0, 0],
                    [3.057, -0.911],
                    [0, 0],
                    [-16.112, 12.99],
                    [0, 0]
                  ],
                  "v": [
                    [11.76, 42.345],
                    [12.701, 42.345],
                    [21.52, 38.553],
                    [67.973, 84.946],
                    [11.76, 108.054]
                  ],
                  "c": true
                },
                "ix": 2
              },
              "nm": "Path 10",
              "mn": "ADBE Vector Shape - Group",
              "hd": false
            },
            {
              "ty": "mm",
              "mm": 1,
              "nm": "Merge Paths 1",
              "mn": "ADBE Vector Filter - Merge",
              "hd": false
            },
            {
              "ty": "fl",
              "c": {
                "a": 0,
                "k": [0.62400004069, 0.788000009574, 0.922000002394, 1],
                "ix": 4
              },
              "o": { "a": 0, "k": 100, "ix": 5 },
              "r": 1,
              "nm": "Fill 1",
              "mn": "ADBE Vector Graphic - Fill",
              "hd": false
            },
            {
              "ty": "tr",
              "p": { "a": 0, "k": [168, 167.5], "ix": 2 },
              "a": { "a": 0, "k": [0, 0], "ix": 1 },
              "s": { "a": 0, "k": [100, 100], "ix": 3 },
              "r": { "a": 0, "k": 0, "ix": 6 },
              "o": { "a": 0, "k": 100, "ix": 7 },
              "sk": { "a": 0, "k": 0, "ix": 4 },
              "sa": { "a": 0, "k": 0, "ix": 5 },
              "nm": "Transform"
            }
          ],
          "nm": "Group 1",
          "np": 12,
          "cix": 2,
          "ix": 1,
          "mn": "ADBE Vector Group",
          "hd": false
        },
        {
          "ty": "gr",
          "it": [
            {
              "ind": 0,
              "ty": "sh",
              "ix": 1,
              "ks": {
                "a": 0,
                "k": {
                  "i": [
                    [3.175, 0],
                    [0, 0],
                    [17.405, 20.641],
                    [0, 0],
                    [0, 3.104],
                    [2.117, 2.247],
                    [3.175, 0],
                    [2.235, -2.16],
                    [0, 0],
                    [26.813, 2.359],
                    [0, 0],
                    [2.117, 2.201],
                    [3.057, 0],
                    [2.234, -2.199],
                    [0, -3.111],
                    [0, 0],
                    [20.697, -17.386],
                    [0, 0],
                    [1.529, 0.702],
                    [1.646, 0.06],
                    [1.529, -0.594],
                    [1.058, -1.149],
                    [0.588, -1.512],
                    [0, -1.623],
                    [-0.706, -1.464],
                    [-1.176, -1.062],
                    [0, 0],
                    [2.351, -26.884],
                    [0, 0],
                    [2.235, -2.201],
                    [0, -3.111],
                    [-2.116, -2.199],
                    [-3.175, 0],
                    [0, 0],
                    [-17.405, -20.64],
                    [0, 0],
                    [0.705, -1.466],
                    [0.118, -1.624],
                    [-0.588, -1.512],
                    [-1.177, -1.149],
                    [-1.529, -0.594],
                    [-1.529, 0.059],
                    [-1.411, 0.703],
                    [-1.059, 1.23],
                    [0, 0],
                    [-26.813, -2.359],
                    [0, 0],
                    [-2.117, -2.199],
                    [-3.058, 0],
                    [-2.234, 2.2],
                    [0, 3.111],
                    [0, 0],
                    [-20.698, 17.387],
                    [0, 0],
                    [-3.058, 0],
                    [-2.235, 2.14],
                    [0, 3.109],
                    [2.117, 2.237],
                    [0, 0],
                    [-2.352, 26.885],
                    [0, 0],
                    [-2.235, 2.2],
                    [0, 3.112],
                    [2.116, 2.198]
                  ],
                  "o": [
                    [0, 0],
                    [-2.352, -26.884],
                    [0, 0],
                    [2.117, -2.247],
                    [0, -3.103],
                    [-2.235, -2.16],
                    [-3.058, 0],
                    [0, 0],
                    [-20.698, -17.386],
                    [0, 0],
                    [0, -3.111],
                    [-2.234, -2.199],
                    [-3.058, 0],
                    [-2.117, 2.201],
                    [0, 0],
                    [-26.813, 2.359],
                    [0, 0],
                    [-1.059, -1.229],
                    [-1.411, -0.703],
                    [-1.529, -0.059],
                    [-1.529, 0.594],
                    [-1.177, 1.149],
                    [-0.588, 1.512],
                    [0.118, 1.624],
                    [0.705, 1.465],
                    [0, 0],
                    [-17.405, 20.641],
                    [0, 0],
                    [-3.175, 0],
                    [-2.116, 2.198],
                    [0, 3.112],
                    [2.235, 2.2],
                    [0, 0],
                    [2.351, 26.885],
                    [0, 0],
                    [-1.176, 1.062],
                    [-0.706, 1.463],
                    [0, 1.624],
                    [0.588, 1.512],
                    [1.058, 1.149],
                    [1.529, 0.595],
                    [1.646, -0.059],
                    [1.529, -0.702],
                    [0, 0],
                    [20.697, 17.387],
                    [0, 0],
                    [0, 3.111],
                    [2.234, 2.2],
                    [3.057, 0],
                    [2.117, -2.199],
                    [0, 0],
                    [26.813, -2.359],
                    [0, 0],
                    [2.235, 2.14],
                    [3.175, 0],
                    [2.117, -2.237],
                    [0, -3.111],
                    [0, 0],
                    [17.405, -20.64],
                    [0, 0],
                    [3.175, 0],
                    [2.116, -2.199],
                    [0, -3.111],
                    [-2.235, -2.201]
                  ],
                  "v": [
                    [155.819, -11.81],
                    [131.711, -11.81],
                    [101.37, -84.839],
                    [118.54, -101.95],
                    [121.833, -110.285],
                    [118.54, -118.62],
                    [110.19, -121.988],
                    [101.84, -118.62],
                    [84.789, -101.509],
                    [11.759, -131.85],
                    [11.759, -155.928],
                    [8.349, -164.223],
                    [0, -167.658],
                    [-8.35, -164.223],
                    [-11.76, -155.928],
                    [-11.76, -131.85],
                    [-84.789, -101.509],
                    [-101.841, -118.62],
                    [-105.722, -121.549],
                    [-110.426, -122.705],
                    [-115.13, -121.894],
                    [-119.128, -119.251],
                    [-121.833, -115.217],
                    [-122.657, -110.463],
                    [-121.48, -105.781],
                    [-118.54, -101.95],
                    [-101.371, -84.839],
                    [-131.711, -11.81],
                    [-155.819, -11.81],
                    [-164.169, -8.373],
                    [-167.579, -0.08],
                    [-164.169, 8.215],
                    [-155.819, 11.651],
                    [-131.711, 11.651],
                    [-101.371, 84.68],
                    [-118.54, 101.791],
                    [-121.48, 105.623],
                    [-122.657, 110.304],
                    [-121.833, 115.058],
                    [-119.128, 119.092],
                    [-115.13, 121.735],
                    [-110.426, 122.546],
                    [-105.722, 121.39],
                    [-101.841, 118.461],
                    [-84.789, 101.35],
                    [-11.76, 131.691],
                    [-11.76, 155.769],
                    [-8.35, 164.063],
                    [0, 167.5],
                    [8.349, 164.063],
                    [11.759, 155.769],
                    [11.759, 131.691],
                    [84.789, 101.35],
                    [101.84, 118.461],
                    [110.19, 121.795],
                    [118.54, 118.461],
                    [121.95, 110.127],
                    [118.54, 101.791],
                    [101.37, 84.68],
                    [131.711, 11.651],
                    [155.819, 11.651],
                    [164.169, 8.215],
                    [167.579, -0.08],
                    [164.169, -8.373]
                  ],
                  "c": true
                },
                "ix": 2
              },
              "nm": "Path 1",
              "mn": "ADBE Vector Shape - Group",
              "hd": false
            },
            {
              "ind": 1,
              "ty": "sh",
              "ix": 2,
              "ks": {
                "a": 0,
                "k": {
                  "i": [
                    [0, 0],
                    [-15.994, -13.202],
                    [0, 0],
                    [3.175, 0.91],
                    [0, 0]
                  ],
                  "o": [
                    [20.581, 2.096],
                    [0, 0],
                    [-2.705, -1.61],
                    [0, 0],
                    [0, 0]
                  ],
                  "v": [
                    [11.759, -108.212],
                    [67.972, -84.751],
                    [21.638, -38.446],
                    [12.818, -42.239],
                    [11.878, -42.239]
                  ],
                  "c": true
                },
                "ix": 2
              },
              "nm": "Path 2",
              "mn": "ADBE Vector Shape - Group",
              "hd": false
            },
            {
              "ind": 2,
              "ty": "sh",
              "ix": 3,
              "ks": {
                "a": 0,
                "k": {
                  "i": [
                    [-20.58, 2.088],
                    [0, 0],
                    [0, 0],
                    [2.822, -1.61],
                    [0, 0]
                  ],
                  "o": [
                    [0, 0],
                    [0, 0],
                    [-3.058, 0.91],
                    [0, 0],
                    [16.111, -12.993]
                  ],
                  "v": [
                    [-11.76, -108.212],
                    [-11.76, -42.503],
                    [-12.701, -42.503],
                    [-21.521, -38.711],
                    [-67.973, -85.103]
                  ],
                  "c": true
                },
                "ix": 2
              },
              "nm": "Path 3",
              "mn": "ADBE Vector Shape - Group",
              "hd": false
            },
            {
              "ind": 3,
              "ty": "sh",
              "ix": 4,
              "ks": {
                "a": 0,
                "k": {
                  "i": [
                    [-13.171, 15.981],
                    [0, 0],
                    [0.941, -3.089],
                    [0, 0],
                    [0, 0]
                  ],
                  "o": [
                    [0, 0],
                    [-1.646, 2.768],
                    [0, 0],
                    [0, 0],
                    [2.235, -20.6]
                  ],
                  "v": [
                    [-84.672, -68.081],
                    [-38.338, -21.776],
                    [-42.219, -12.956],
                    [-42.219, -11.986],
                    [-108.192, -11.986]
                  ],
                  "c": true
                },
                "ix": 2
              },
              "nm": "Path 4",
              "mn": "ADBE Vector Shape - Group",
              "hd": false
            },
            {
              "ind": 4,
              "ty": "sh",
              "ix": 5,
              "ks": {
                "a": 0,
                "k": {
                  "i": [
                    [0, 0],
                    [0, 0],
                    [0, 0],
                    [-1.646, -2.779],
                    [0, 0],
                    [2.235, 20.451]
                  ],
                  "o": [
                    [0, 0],
                    [0, 0],
                    [0.94, 3.079],
                    [0, 0],
                    [-12.935, -15.989],
                    [0, 0]
                  ],
                  "v": [
                    [-108.192, 11.298],
                    [-42.453, 11.298],
                    [-42.453, 12.269],
                    [-38.573, 21.088],
                    [-85.025, 67.481],
                    [-108.192, 11.651]
                  ],
                  "c": true
                },
                "ix": 2
              },
              "nm": "Path 5",
              "mn": "ADBE Vector Shape - Group",
              "hd": false
            },
            {
              "ind": 5,
              "ty": "sh",
              "ix": 6,
              "ks": {
                "a": 0,
                "k": {
                  "i": [
                    [0, 0],
                    [15.994, 13.202],
                    [0, 0],
                    [-3.175, -0.888],
                    [0, 0]
                  ],
                  "o": [
                    [-20.58, -2.095],
                    [0, 0],
                    [2.705, 1.63],
                    [0, 0],
                    [0, 0]
                  ],
                  "v": [
                    [-11.76, 108.053],
                    [-67.973, 84.592],
                    [-21.639, 38.288],
                    [-12.819, 42.08],
                    [-11.878, 42.08]
                  ],
                  "c": true
                },
                "ix": 2
              },
              "nm": "Path 6",
              "mn": "ADBE Vector Shape - Group",
              "hd": false
            },
            {
              "ind": 6,
              "ty": "sh",
              "ix": 7,
              "ks": {
                "a": 0,
                "k": {
                  "i": [
                    [0, 0],
                    [2.47, 0.47],
                    [2.469, 1.702],
                    [1.411, 2.03],
                    [0.47, 2.919],
                    [-0.588, 2.387],
                    [-1.647, 2.425],
                    [-2, 1.411],
                    [-2.94, 0.506],
                    [-2.47, -0.47],
                    [-2.469, -1.701],
                    [-1.411, -2.029],
                    [-0.47, -2.919],
                    [0.588, -2.387],
                    [1.647, -2.424],
                    [1.999, -1.411],
                    [2.941, -0.612]
                  ],
                  "o": [
                    [-2.47, 0.47],
                    [-2.94, -0.506],
                    [-2, -1.411],
                    [-1.647, -2.424],
                    [-0.588, -2.387],
                    [0.47, -2.919],
                    [1.411, -2.029],
                    [2.469, -1.701],
                    [2.47, -0.47],
                    [2.941, 0.506],
                    [1.999, 1.411],
                    [1.647, 2.425],
                    [0.588, 2.387],
                    [-0.47, 2.919],
                    [-1.411, 2.03],
                    [-2.469, 1.827],
                    [0, 0]
                  ],
                  "v": [
                    [3.645, 19.854],
                    [-3.646, 19.854],
                    [-11.76, 16.502],
                    [-16.934, 11.298],
                    [-20.227, 3.184],
                    [-20.227, -4.048],
                    [-16.934, -12.163],
                    [-11.76, -17.367],
                    [-3.646, -20.718],
                    [3.645, -20.718],
                    [11.759, -17.367],
                    [16.934, -12.163],
                    [20.227, -4.048],
                    [20.227, 3.184],
                    [16.934, 11.298],
                    [11.759, 16.502],
                    [3.645, 20.207]
                  ],
                  "c": true
                },
                "ix": 2
              },
              "nm": "Path 7",
              "mn": "ADBE Vector Shape - Group",
              "hd": false
            },
            {
              "ind": 7,
              "ty": "sh",
              "ix": 8,
              "ks": {
                "a": 0,
                "k": {
                  "i": [
                    [20.581, -2.088],
                    [0, 0],
                    [0, 0],
                    [-2.822, 1.61],
                    [0, 0]
                  ],
                  "o": [
                    [0, 0],
                    [0, 0],
                    [3.057, -0.91],
                    [0, 0],
                    [-16.111, 12.991]
                  ],
                  "v": [
                    [11.759, 108.053],
                    [11.759, 42.344],
                    [12.701, 42.344],
                    [21.52, 38.552],
                    [67.972, 84.945]
                  ],
                  "c": true
                },
                "ix": 2
              },
              "nm": "Path 8",
              "mn": "ADBE Vector Shape - Group",
              "hd": false
            },
            {
              "ind": 8,
              "ty": "sh",
              "ix": 9,
              "ks": {
                "a": 0,
                "k": {
                  "i": [
                    [13.052, -16.013],
                    [0, 0],
                    [-0.94, 3.08],
                    [0, 0],
                    [0, 0]
                  ],
                  "o": [
                    [0, 0],
                    [1.646, -2.78],
                    [0, 0],
                    [0, 0],
                    [-2, 20.57]
                  ],
                  "v": [
                    [84.672, 67.922],
                    [38.337, 21.618],
                    [42.217, 12.797],
                    [42.217, 11.828],
                    [107.839, 11.828]
                  ],
                  "c": true
                },
                "ix": 2
              },
              "nm": "Path 9",
              "mn": "ADBE Vector Shape - Group",
              "hd": false
            },
            {
              "ind": 9,
              "ty": "sh",
              "ix": 10,
              "ks": {
                "a": 0,
                "k": {
                  "i": [
                    [0, 0],
                    [0, 0],
                    [1.646, 2.779],
                    [0, 0],
                    [-2.117, -20.663]
                  ],
                  "o": [
                    [0, 0],
                    [-0.941, -3.08],
                    [0, 0],
                    [13.171, 16.106],
                    [0, 0]
                  ],
                  "v": [
                    [42.453, -11.457],
                    [42.453, -12.427],
                    [38.572, -21.247],
                    [85.024, -67.64],
                    [108.426, -11.281]
                  ],
                  "c": true
                },
                "ix": 2
              },
              "nm": "Path 10",
              "mn": "ADBE Vector Shape - Group",
              "hd": false
            },
            {
              "ty": "mm",
              "mm": 1,
              "nm": "Merge Paths 1",
              "mn": "ADBE Vector Filter - Merge",
              "hd": false
            },
            {
              "ty": "fl",
              "c": {
                "a": 0,
                "k": [0.62400004069, 0.788000009574, 0.922000002394, 1],
                "ix": 4
              },
              "o": { "a": 0, "k": 100, "ix": 5 },
              "r": 1,
              "nm": "Fill 1",
              "mn": "ADBE Vector Graphic - Fill",
              "hd": false
            },
            {
              "ty": "tr",
              "p": { "a": 0, "k": [168, 167.5], "ix": 2 },
              "a": { "a": 0, "k": [0, 0], "ix": 1 },
              "s": { "a": 0, "k": [100, 100], "ix": 3 },
              "r": { "a": 0, "k": 0, "ix": 6 },
              "o": { "a": 0, "k": 100, "ix": 7 },
              "sk": { "a": 0, "k": 0, "ix": 4 },
              "sa": { "a": 0, "k": 0, "ix": 5 },
              "nm": "Transform"
            }
          ],
          "nm": "Group 2",
          "np": 14,
          "cix": 2,
          "ix": 2,
          "mn": "ADBE Vector Group",
          "hd": false
        }
      ],
      "ip": 0,
      "op": 61.0000024845809,
      "st": 0,
      "bm": 0
    },
    {
      "ddd": 0,
      "ind": 3,
      "ty": 4,
      "nm": "icon-boat Outlines",
      "sr": 1,
      "ks": {
        "o": {
          "a": 1,
          "k": [
            {
              "i": { "x": [0.833], "y": [0.833] },
              "o": { "x": [0.167], "y": [0.167] },
              "n": ["0p833_0p833_0p167_0p167"],
              "t": 53,
              "s": [0],
              "e": [73]
            },
            {
              "i": { "x": [0.833], "y": [0.833] },
              "o": { "x": [0.167], "y": [0.167] },
              "n": ["0p833_0p833_0p167_0p167"],
              "t": 80,
              "s": [73],
              "e": [0]
            },
            { "t": 121.000004928431 }
          ],
          "ix": 11
        },
        "r": { "a": 0, "k": 0, "ix": 10 },
        "p": { "a": 0, "k": [50, 50.5, 0], "ix": 2 },
        "a": { "a": 0, "k": [168, 167.5, 0], "ix": 1 },
        "s": { "a": 0, "k": [30, 30, 100], "ix": 6 }
      },
      "ao": 0,
      "shapes": [
        {
          "ty": "gr",
          "it": [
            {
              "ind": 0,
              "ty": "sh",
              "ix": 1,
              "ks": {
                "a": 0,
                "k": {
                  "i": [
                    [0, 0],
                    [0, 0],
                    [0, 0],
                    [0, 0],
                    [0, 0],
                    [0, 0],
                    [0, 0]
                  ],
                  "o": [
                    [0, 0],
                    [0, 0],
                    [0, 0],
                    [0, 0],
                    [0, 0],
                    [0, 0],
                    [0, 0]
                  ],
                  "v": [
                    [40.533, -27.13],
                    [15.69, 10.134],
                    [-68.643, 10.134],
                    [-78.45, 27.13],
                    [78.449, 27.13],
                    [78.449, 10.134],
                    [78.449, -27.13]
                  ],
                  "c": true
                },
                "ix": 2
              },
              "nm": "Path 1",
              "mn": "ADBE Vector Shape - Group",
              "hd": false
            },
            {
              "ind": 1,
              "ty": "sh",
              "ix": 2,
              "ks": {
                "a": 0,
                "k": {
                  "i": [
                    [0, 0],
                    [0, 0],
                    [0, 0],
                    [0, 0]
                  ],
                  "o": [
                    [0, 0],
                    [0, 0],
                    [0, 0],
                    [0, 0]
                  ],
                  "v": [
                    [49.684, -9.479],
                    [60.798, -9.479],
                    [60.798, 10.134],
                    [35.955, 10.134]
                  ],
                  "c": true
                },
                "ix": 2
              },
              "nm": "Path 2",
              "mn": "ADBE Vector Shape - Group",
              "hd": false
            },
            {
              "ty": "mm",
              "mm": 1,
              "nm": "Merge Paths 1",
              "mn": "ADBE Vector Filter - Merge",
              "hd": false
            },
            {
              "ty": "fl",
              "c": {
                "a": 0,
                "k": [0.62400004069, 0.788000009574, 0.922000002394, 1],
                "ix": 4
              },
              "o": { "a": 0, "k": 100, "ix": 5 },
              "r": 1,
              "nm": "Fill 1",
              "mn": "ADBE Vector Graphic - Fill",
              "hd": false
            },
            {
              "ty": "tr",
              "p": { "a": 0, "k": [168.982, 107.446], "ix": 2 },
              "a": { "a": 0, "k": [0, 0], "ix": 1 },
              "s": { "a": 0, "k": [100, 100], "ix": 3 },
              "r": { "a": 0, "k": 0, "ix": 6 },
              "o": { "a": 0, "k": 100, "ix": 7 },
              "sk": { "a": 0, "k": 0, "ix": 4 },
              "sa": { "a": 0, "k": 0, "ix": 5 },
              "nm": "Transform"
            }
          ],
          "nm": "Group 1",
          "np": 4,
          "cix": 2,
          "ix": 1,
          "mn": "ADBE Vector Group",
          "hd": false
        },
        {
          "ty": "gr",
          "it": [
            {
              "ind": 0,
              "ty": "sh",
              "ix": 1,
              "ks": {
                "a": 0,
                "k": {
                  "i": [
                    [0, 0],
                    [0, 0],
                    [1.307, -0.655],
                    [9.152, 0],
                    [0, 0],
                    [-7.844, 4.576],
                    [-9.153, 0],
                    [-6.537, -4.577],
                    [-15.037, 0],
                    [-7.846, 4.576],
                    [-9.152, 0],
                    [-6.538, -4.577],
                    [-15.036, 0],
                    [-7.845, 4.576],
                    [-9.153, 0],
                    [0, 0],
                    [5.23, -2.615],
                    [0, 0]
                  ],
                  "o": [
                    [0, 0],
                    [-1.306, 0.654],
                    [-6.538, 4.575],
                    [0, 0],
                    [14.382, 0],
                    [6.538, -4.577],
                    [9.152, 0],
                    [7.844, 5.229],
                    [14.381, 0],
                    [6.536, -4.577],
                    [9.152, 0],
                    [7.845, 5.229],
                    [14.383, 0],
                    [6.537, -4.577],
                    [0, 0],
                    [-9.153, -0.654],
                    [0, 0],
                    [0, 0]
                  ],
                  "v": [
                    [-135.652, -39.878],
                    [-101.004, 12.422],
                    [-104.271, 14.384],
                    [-125.845, 22.228],
                    [-125.845, 39.879],
                    [-94.466, 29.42],
                    [-73.545, 21.574],
                    [-52.626, 29.42],
                    [-21.246, 39.879],
                    [10.134, 29.42],
                    [31.053, 21.574],
                    [51.973, 29.42],
                    [83.352, 39.879],
                    [114.732, 29.42],
                    [135.652, 21.574],
                    [135.652, 3.924],
                    [115.386, 7.845],
                    [97.735, -39.878]
                  ],
                  "c": true
                },
                "ix": 2
              },
              "nm": "Path 1",
              "mn": "ADBE Vector Shape - Group",
              "hd": false
            },
            {
              "ind": 1,
              "ty": "sh",
              "ix": 2,
              "ks": {
                "a": 0,
                "k": {
                  "i": [
                    [0, 0],
                    [0, 0],
                    [0, 0],
                    [7.844, 0],
                    [7.191, 3.921],
                    [13.729, 0],
                    [7.191, -4.577],
                    [9.152, 0],
                    [6.537, 4.575],
                    [13.729, 0],
                    [3.268, -0.654]
                  ],
                  "o": [
                    [0, 0],
                    [0, 0],
                    [-5.23, 3.269],
                    [-9.806, 0],
                    [-7.846, -5.231],
                    [-14.382, 0],
                    [-6.537, 4.575],
                    [-9.153, 0],
                    [-7.845, -5.231],
                    [-3.923, 0],
                    [0, 0]
                  ],
                  "v": [
                    [-102.964, -22.227],
                    [85.968, -22.227],
                    [100.35, 16.997],
                    [82.699, 22.228],
                    [60.472, 14.384],
                    [30.399, 3.924],
                    [0.327, 14.384],
                    [-21.246, 22.228],
                    [-42.82, 14.384],
                    [-72.892, 3.924],
                    [-84.005, 5.23]
                  ],
                  "c": true
                },
                "ix": 2
              },
              "nm": "Path 2",
              "mn": "ADBE Vector Shape - Group",
              "hd": false
            },
            {
              "ty": "mm",
              "mm": 1,
              "nm": "Merge Paths 1",
              "mn": "ADBE Vector Filter - Merge",
              "hd": false
            },
            {
              "ty": "fl",
              "c": {
                "a": 0,
                "k": [0.62400004069, 0.788000009574, 0.922000002394, 1],
                "ix": 4
              },
              "o": { "a": 0, "k": 100, "ix": 5 },
              "r": 1,
              "nm": "Fill 1",
              "mn": "ADBE Vector Graphic - Fill",
              "hd": false
            },
            {
              "ty": "tr",
              "p": { "a": 0, "k": [167.348, 198.643], "ix": 2 },
              "a": { "a": 0, "k": [0, 0], "ix": 1 },
              "s": { "a": 0, "k": [100, 100], "ix": 3 },
              "r": { "a": 0, "k": 0, "ix": 6 },
              "o": { "a": 0, "k": 100, "ix": 7 },
              "sk": { "a": 0, "k": 0, "ix": 4 },
              "sa": { "a": 0, "k": 0, "ix": 5 },
              "nm": "Transform"
            }
          ],
          "nm": "Group 2",
          "np": 4,
          "cix": 2,
          "ix": 2,
          "mn": "ADBE Vector Group",
          "hd": false
        }
      ],
      "ip": 54.0000021994651,
      "op": 122.000004969162,
      "st": 61.0000024845809,
      "bm": 0
    },
    {
      "ddd": 0,
      "ind": 5,
      "ty": 4,
      "nm": "icon-route Outlines",
      "sr": 1,
      "ks": {
        "o": {
          "a": 1,
          "k": [
            {
              "i": { "x": [0.833], "y": [0.833] },
              "o": { "x": [0.167], "y": [0.167] },
              "n": ["0p833_0p833_0p167_0p167"],
              "t": 115,
              "s": [0],
              "e": [100]
            },
            {
              "i": { "x": [0.833], "y": [0.833] },
              "o": { "x": [0.167], "y": [0.167] },
              "n": ["0p833_0p833_0p167_0p167"],
              "t": 153,
              "s": [100],
              "e": [0]
            },
            { "t": 179.000007290819 }
          ],
          "ix": 11
        },
        "r": { "a": 0, "k": 0, "ix": 10 },
        "p": { "a": 0, "k": [50, 50, 0], "ix": 2 },
        "a": { "a": 0, "k": [168, 167.5, 0], "ix": 1 },
        "s": { "a": 0, "k": [30, 30, 100], "ix": 6 }
      },
      "ao": 0,
      "shapes": [
        {
          "ty": "gr",
          "it": [
            {
              "ind": 0,
              "ty": "sh",
              "ix": 1,
              "ks": {
                "a": 0,
                "k": {
                  "i": [
                    [0, 0],
                    [0, 0],
                    [0, 0],
                    [0, 0]
                  ],
                  "o": [
                    [0, 0],
                    [0, 0],
                    [0, 0],
                    [0, 0]
                  ],
                  "v": [
                    [-8.867, 9.434],
                    [8.867, 9.434],
                    [8.867, -9.434],
                    [-8.867, -9.434]
                  ],
                  "c": true
                },
                "ix": 2
              },
              "nm": "Path 1",
              "mn": "ADBE Vector Shape - Group",
              "hd": false
            },
            {
              "ty": "fl",
              "c": {
                "a": 0,
                "k": [0.62400004069, 0.788000009574, 0.922000002394, 1],
                "ix": 4
              },
              "o": { "a": 0, "k": 100, "ix": 5 },
              "r": 1,
              "nm": "Fill 1",
              "mn": "ADBE Vector Graphic - Fill",
              "hd": false
            },
            {
              "ty": "tr",
              "p": { "a": 0, "k": [112.233, 121.24], "ix": 2 },
              "a": { "a": 0, "k": [0, 0], "ix": 1 },
              "s": { "a": 0, "k": [100, 100], "ix": 3 },
              "r": { "a": 0, "k": 0, "ix": 6 },
              "o": { "a": 0, "k": 100, "ix": 7 },
              "sk": { "a": 0, "k": 0, "ix": 4 },
              "sa": { "a": 0, "k": 0, "ix": 5 },
              "nm": "Transform"
            }
          ],
          "nm": "Group 1",
          "np": 2,
          "cix": 2,
          "ix": 1,
          "mn": "ADBE Vector Group",
          "hd": false
        },
        {
          "ty": "gr",
          "it": [
            {
              "ind": 0,
              "ty": "sh",
              "ix": 1,
              "ks": {
                "a": 0,
                "k": {
                  "i": [
                    [0.013, 0],
                    [0, 0],
                    [0, 0],
                    [0, 0],
                    [-3.679, -1.916],
                    [0, 0],
                    [7.139, 0]
                  ],
                  "o": [
                    [0, 0],
                    [0, 0],
                    [0, 0],
                    [4.148, -0.005],
                    [0, 0],
                    [-6.352, -3.263],
                    [-0.014, 0]
                  ],
                  "v": [
                    [16.971, -98.097],
                    [-0.691, -98.097],
                    [-0.691, -79.229],
                    [16.971, -79.229],
                    [28.887, -76.32],
                    [37.54, -93.131],
                    [17.01, -98.097]
                  ],
                  "c": true
                },
                "ix": 2
              },
              "nm": "Path 1",
              "mn": "ADBE Vector Shape - Group",
              "hd": false
            },
            {
              "ind": 1,
              "ty": "sh",
              "ix": 2,
              "ks": {
                "a": 0,
                "k": {
                  "i": [
                    [0, 0],
                    [0.018, -6.195],
                    [0.655, -2.305],
                    [0, 0],
                    [0.014, 3.978],
                    [7.012, 8.097]
                  ],
                  "o": [
                    [4.044, 4.694],
                    [0.044, 2.397],
                    [0, 0],
                    [1.049, -3.836],
                    [-0.036, -10.712],
                    [0, 0]
                  ],
                  "v": [
                    [36.76, -70.079],
                    [43.003, -53.197],
                    [42.079, -46.105],
                    [60.309, -41.423],
                    [61.87, -53.197],
                    [50.945, -82.349]
                  ],
                  "c": true
                },
                "ix": 2
              },
              "nm": "Path 2",
              "mn": "ADBE Vector Shape - Group",
              "hd": false
            },
            {
              "ind": 2,
              "ty": "sh",
              "ix": 3,
              "ks": {
                "a": 0,
                "k": {
                  "i": [
                    [3.584, -1.773],
                    [3.998, 0.023],
                    [0, 0],
                    [0, 0],
                    [0, 0],
                    [-6.153, 3.052],
                    [-4.156, 5.47],
                    [0, 0]
                  ],
                  "o": [
                    [-3.583, 1.774],
                    [0, 0],
                    [0, 0],
                    [0, 0],
                    [6.867, 0.001],
                    [6.152, -3.051],
                    [0, 0],
                    [-2.408, 3.193]
                  ],
                  "v": [
                    [28.499, -29.828],
                    [16.971, -27.166],
                    [14.984, -27.166],
                    [14.984, -8.298],
                    [16.971, -8.298],
                    [36.764, -12.937],
                    [52.436, -25.89],
                    [37.611, -37.38]
                  ],
                  "c": true
                },
                "ix": 2
              },
              "nm": "Path 3",
              "mn": "ADBE Vector Shape - Group",
              "hd": false
            },
            {
              "ind": 3,
              "ty": "sh",
              "ix": 4,
              "ks": {
                "a": 0,
                "k": {
                  "i": [
                    [6.68, -2.442],
                    [0, 0],
                    [-5.005, -0.012],
                    [0, 0],
                    [0, 0],
                    [0, 0],
                    [0.143, 0]
                  ],
                  "o": [
                    [0, 0],
                    [4.708, -1.7],
                    [0, 0],
                    [0, 0],
                    [0, 0],
                    [-0.143, -0.001],
                    [-7.112, 0]
                  ],
                  "v": [
                    [-36.086, -23.477],
                    [-29.702, -5.745],
                    [-15.02, -8.298],
                    [1.436, -8.298],
                    [1.436, -27.166],
                    [-14.807, -27.166],
                    [-15.236, -27.168]
                  ],
                  "c": true
                },
                "ix": 2
              },
              "nm": "Path 4",
              "mn": "ADBE Vector Shape - Group",
              "hd": false
            },
            {
              "ind": 4,
              "ty": "sh",
              "ix": 5,
              "ks": {
                "a": 0,
                "k": {
                  "i": [
                    [4.332, -12.951],
                    [0, 0],
                    [-7.866, 5.425],
                    [0, 0]
                  ],
                  "o": [
                    [0, 0],
                    [2.995, -9.073],
                    [0, 0],
                    [-11.231, 7.769]
                  ],
                  "v": [
                    [-74.458, 15.818],
                    [-56.514, 21.776],
                    [-39.773, -0.567],
                    [-50.484, -16.1]
                  ],
                  "c": true
                },
                "ix": 2
              },
              "nm": "Path 5",
              "mn": "ADBE Vector Shape - Group",
              "hd": false
            },
            {
              "ind": 5,
              "ty": "sh",
              "ix": 6,
              "ks": {
                "a": 0,
                "k": {
                  "i": [
                    [0, 0],
                    [-6.923, -10.266],
                    [0, 0],
                    [-0.106, 8.613],
                    [0, 0],
                    [0, 0]
                  ],
                  "o": [
                    [-0.036, 12.383],
                    [0, 0],
                    [-4.73, -7.199],
                    [0, 0],
                    [0, 0],
                    [0, 0]
                  ],
                  "v": [
                    [-77.579, 35.465],
                    [-67.012, 70.221],
                    [-51.691, 59.724],
                    [-58.784, 35.465],
                    [-58.784, 32.841],
                    [-77.579, 31.707]
                  ],
                  "c": true
                },
                "ix": 2
              },
              "nm": "Path 6",
              "mn": "ADBE Vector Shape - Group",
              "hd": false
            },
            {
              "ind": 6,
              "ty": "sh",
              "ix": 7,
              "ks": {
                "a": 0,
                "k": {
                  "i": [
                    [0, 0],
                    [-13.623, -0.999],
                    [0, 0],
                    [7.07, 6.243]
                  ],
                  "o": [
                    [10.206, 9.077],
                    [0, 0],
                    [-9.405, -0.705],
                    [0, 0]
                  ],
                  "v": [
                    [-56.372, 82.563],
                    [-19.63, 98.097],
                    [-18.495, 79.087],
                    [-43.887, 68.377]
                  ],
                  "c": true
                },
                "ix": 2
              },
              "nm": "Path 7",
              "mn": "ADBE Vector Shape - Group",
              "hd": false
            },
            {
              "ind": 7,
              "ty": "sh",
              "ix": 8,
              "ks": {
                "a": 0,
                "k": {
                  "i": [
                    [0, 0],
                    [0, 0],
                    [0, 0],
                    [0, 0]
                  ],
                  "o": [
                    [0, 0],
                    [0, 0],
                    [0, 0],
                    [0, 0]
                  ],
                  "v": [
                    [43.145, 98.097],
                    [77.615, 98.097],
                    [77.615, 79.229],
                    [43.145, 79.229]
                  ],
                  "c": true
                },
                "ix": 2
              },
              "nm": "Path 8",
              "mn": "ADBE Vector Shape - Group",
              "hd": false
            },
            {
              "ind": 8,
              "ty": "sh",
              "ix": 9,
              "ks": {
                "a": 0,
                "k": {
                  "i": [[0, 0]],
                  "o": [[0, 0]],
                  "v": [[43.145, 79.229]],
                  "c": false
                },
                "ix": 2
              },
              "nm": "Path 9",
              "mn": "ADBE Vector Shape - Group",
              "hd": false
            },
            {
              "ind": 9,
              "ty": "sh",
              "ix": 10,
              "ks": {
                "a": 0,
                "k": {
                  "i": [
                    [0, 0],
                    [0, 0],
                    [0, 0],
                    [0, 0]
                  ],
                  "o": [
                    [0, 0],
                    [0, 0],
                    [0, 0],
                    [0, 0]
                  ],
                  "v": [
                    [-5.16, 98.097],
                    [29.383, 98.097],
                    [29.383, 79.229],
                    [-5.16, 79.229]
                  ],
                  "c": true
                },
                "ix": 2
              },
              "nm": "Path 10",
              "mn": "ADBE Vector Shape - Group",
              "hd": false
            },
            {
              "ty": "mm",
              "mm": 1,
              "nm": "Merge Paths 1",
              "mn": "ADBE Vector Filter - Merge",
              "hd": false
            },
            {
              "ty": "fl",
              "c": {
                "a": 0,
                "k": [0.62400004069, 0.788000009574, 0.922000002394, 1],
                "ix": 4
              },
              "o": { "a": 0, "k": 100, "ix": 5 },
              "r": 1,
              "nm": "Fill 1",
              "mn": "ADBE Vector Graphic - Fill",
              "hd": false
            },
            {
              "ty": "tr",
              "p": { "a": 0, "k": [136.048, 209.903], "ix": 2 },
              "a": { "a": 0, "k": [0, 0], "ix": 1 },
              "s": { "a": 0, "k": [100, 100], "ix": 3 },
              "r": { "a": 0, "k": 0, "ix": 6 },
              "o": { "a": 0, "k": 100, "ix": 7 },
              "sk": { "a": 0, "k": 0, "ix": 4 },
              "sa": { "a": 0, "k": 0, "ix": 5 },
              "nm": "Transform"
            }
          ],
          "nm": "Group 2",
          "np": 12,
          "cix": 2,
          "ix": 2,
          "mn": "ADBE Vector Group",
          "hd": false
        },
        {
          "ty": "gr",
          "it": [
            {
              "ind": 0,
              "ty": "sh",
              "ix": 1,
              "ks": {
                "a": 0,
                "k": {
                  "i": [
                    [0, 0],
                    [0, 0],
                    [0, 0],
                    [0, 0]
                  ],
                  "o": [
                    [0, 0],
                    [0, 0],
                    [0, 0],
                    [0, 0]
                  ],
                  "v": [
                    [-8.867, 9.434],
                    [8.867, 9.434],
                    [8.867, -9.434],
                    [-8.867, -9.434]
                  ],
                  "c": true
                },
                "ix": 2
              },
              "nm": "Path 1",
              "mn": "ADBE Vector Shape - Group",
              "hd": false
            },
            {
              "ty": "fl",
              "c": {
                "a": 0,
                "k": [0.62400004069, 0.788000009574, 0.922000002394, 1],
                "ix": 4
              },
              "o": { "a": 0, "k": 100, "ix": 5 },
              "r": 1,
              "nm": "Fill 1",
              "mn": "ADBE Vector Graphic - Fill",
              "hd": false
            },
            {
              "ty": "tr",
              "p": { "a": 0, "k": [236.361, 298.566], "ix": 2 },
              "a": { "a": 0, "k": [0, 0], "ix": 1 },
              "s": { "a": 0, "k": [100, 100], "ix": 3 },
              "r": { "a": 0, "k": 0, "ix": 6 },
              "o": { "a": 0, "k": 100, "ix": 7 },
              "sk": { "a": 0, "k": 0, "ix": 4 },
              "sa": { "a": 0, "k": 0, "ix": 5 },
              "nm": "Transform"
            }
          ],
          "nm": "Group 3",
          "np": 2,
          "cix": 2,
          "ix": 3,
          "mn": "ADBE Vector Group",
          "hd": false
        },
        {
          "ty": "gr",
          "it": [
            {
              "ind": 0,
              "ty": "sh",
              "ix": 1,
              "ks": {
                "a": 0,
                "k": {
                  "i": [
                    [6.669, -6.594],
                    [0.054, -9.444],
                    [-6.639, -6.716],
                    [-6.952, -12.382],
                    [-9.837, 10.24],
                    [0, 9.349],
                    [6.508, 6.711],
                    [9.446, 0.053],
                    [0.066, 0]
                  ],
                  "o": [
                    [-6.715, 6.641],
                    [-0.053, 9.445],
                    [9.861, 10.22],
                    [6.978, -12.366],
                    [6.508, -6.71],
                    [0, -9.347],
                    [-6.641, -6.715],
                    [-0.065, 0],
                    [-9.372, 0]
                  ],
                  "v": [
                    [-24.942, -37.059],
                    [-35.514, -11.938],
                    [-25.226, 13.302],
                    [0.096, 47.348],
                    [25.419, 13.302],
                    [35.567, -11.738],
                    [25.419, -36.775],
                    [0.296, -47.347],
                    [0.099, -47.348]
                  ],
                  "c": true
                },
                "ix": 2
              },
              "nm": "Path 1",
              "mn": "ADBE Vector Shape - Group",
              "hd": false
            },
            {
              "ind": 1,
              "ty": "sh",
              "ix": 2,
              "ks": {
                "a": 0,
                "k": {
                  "i": [
                    [2.332, 1.559],
                    [1.074, 2.593],
                    [-0.547, 2.752],
                    [-1.985, 1.982],
                    [-2.752, 0.547],
                    [-2.592, -1.074],
                    [-1.559, -2.333],
                    [0, -2.804],
                    [2.66, -2.66],
                    [3.763, 0]
                  ],
                  "o": [
                    [-2.334, -1.559],
                    [-1.073, -2.59],
                    [0.549, -2.753],
                    [1.983, -1.985],
                    [2.752, -0.546],
                    [2.592, 1.073],
                    [1.559, 2.332],
                    [0, 3.763],
                    [-2.661, 2.661],
                    [-2.805, 0]
                  ],
                  "v": [
                    [-7.784, 0.059],
                    [-13.01, -6.309],
                    [-13.818, -14.504],
                    [-9.934, -21.767],
                    [-2.671, -25.651],
                    [5.525, -24.842],
                    [11.892, -19.618],
                    [14.282, -11.738],
                    [10.128, -1.706],
                    [0.096, 2.449]
                  ],
                  "c": true
                },
                "ix": 2
              },
              "nm": "Path 2",
              "mn": "ADBE Vector Shape - Group",
              "hd": false
            },
            {
              "ty": "mm",
              "mm": 1,
              "nm": "Merge Paths 1",
              "mn": "ADBE Vector Filter - Merge",
              "hd": false
            },
            {
              "ty": "fl",
              "c": {
                "a": 0,
                "k": [0.62400004069, 0.788000009574, 0.922000002394, 1],
                "ix": 4
              },
              "o": { "a": 0, "k": 100, "ix": 5 },
              "r": 1,
              "nm": "Fill 1",
              "mn": "ADBE Vector Graphic - Fill",
              "hd": false
            },
            {
              "ty": "tr",
              "p": { "a": 0, "k": [245.131, 239.374], "ix": 2 },
              "a": { "a": 0, "k": [0, 0], "ix": 1 },
              "s": { "a": 0, "k": [100, 100], "ix": 3 },
              "r": { "a": 0, "k": 0, "ix": 6 },
              "o": { "a": 0, "k": 100, "ix": 7 },
              "sk": { "a": 0, "k": 0, "ix": 4 },
              "sa": { "a": 0, "k": 0, "ix": 5 },
              "nm": "Transform"
            }
          ],
          "nm": "Group 4",
          "np": 4,
          "cix": 2,
          "ix": 4,
          "mn": "ADBE Vector Group",
          "hd": false
        },
        {
          "ty": "gr",
          "it": [
            {
              "ind": 0,
              "ty": "sh",
              "ix": 1,
              "ks": {
                "a": 0,
                "k": {
                  "i": [
                    [6.669, -6.595],
                    [0.054, -9.443],
                    [-6.639, -6.716],
                    [-6.953, -12.383],
                    [-9.837, 10.24],
                    [0, 9.348],
                    [6.508, 6.71],
                    [9.444, 0.054],
                    [0.066, 0]
                  ],
                  "o": [
                    [-6.715, 6.64],
                    [-0.053, 9.445],
                    [9.86, 10.221],
                    [6.977, -12.366],
                    [6.508, -6.709],
                    [0, -9.347],
                    [-6.64, -6.716],
                    [-0.067, 0],
                    [-9.373, 0]
                  ],
                  "v": [
                    [-24.943, -37.058],
                    [-35.514, -11.938],
                    [-25.227, 13.302],
                    [0.096, 47.348],
                    [25.418, 13.302],
                    [35.567, -11.737],
                    [25.418, -36.775],
                    [0.297, -47.347],
                    [0.096, -47.348]
                  ],
                  "c": true
                },
                "ix": 2
              },
              "nm": "Path 1",
              "mn": "ADBE Vector Shape - Group",
              "hd": false
            },
            {
              "ind": 1,
              "ty": "sh",
              "ix": 2,
              "ks": {
                "a": 0,
                "k": {
                  "i": [
                    [2.332, 1.558],
                    [1.073, 2.593],
                    [-0.546, 2.752],
                    [-1.984, 1.983],
                    [-2.751, 0.547],
                    [-2.592, -1.073],
                    [-1.559, -2.333],
                    [0, -2.805],
                    [2.661, -2.66],
                    [3.762, 0]
                  ],
                  "o": [
                    [-2.333, -1.559],
                    [-1.074, -2.592],
                    [0.548, -2.752],
                    [1.983, -1.985],
                    [2.753, -0.547],
                    [2.592, 1.074],
                    [1.559, 2.334],
                    [0, 3.763],
                    [-2.66, 2.661],
                    [-2.805, 0]
                  ],
                  "v": [
                    [-7.785, 0.059],
                    [-13.01, -6.308],
                    [-13.818, -14.504],
                    [-9.935, -21.767],
                    [-2.672, -25.65],
                    [5.525, -24.843],
                    [11.891, -19.618],
                    [14.282, -11.737],
                    [10.127, -1.706],
                    [0.096, 2.45]
                  ],
                  "c": true
                },
                "ix": 2
              },
              "nm": "Path 2",
              "mn": "ADBE Vector Shape - Group",
              "hd": false
            },
            {
              "ty": "mm",
              "mm": 1,
              "nm": "Merge Paths 1",
              "mn": "ADBE Vector Filter - Merge",
              "hd": false
            },
            {
              "ty": "fl",
              "c": {
                "a": 0,
                "k": [0.62400004069, 0.788000009574, 0.922000002394, 1],
                "ix": 4
              },
              "o": { "a": 0, "k": 100, "ix": 5 },
              "r": 1,
              "nm": "Fill 1",
              "mn": "ADBE Vector Graphic - Fill",
              "hd": false
            },
            {
              "ty": "tr",
              "p": { "a": 0, "k": [103.271, 62.048], "ix": 2 },
              "a": { "a": 0, "k": [0, 0], "ix": 1 },
              "s": { "a": 0, "k": [100, 100], "ix": 3 },
              "r": { "a": 0, "k": 0, "ix": 6 },
              "o": { "a": 0, "k": 100, "ix": 7 },
              "sk": { "a": 0, "k": 0, "ix": 4 },
              "sa": { "a": 0, "k": 0, "ix": 5 },
              "nm": "Transform"
            }
          ],
          "nm": "Group 5",
          "np": 4,
          "cix": 2,
          "ix": 5,
          "mn": "ADBE Vector Group",
          "hd": false
        }
      ],
      "ip": 113.000004602584,
      "op": 179.000007290819,
      "st": 149.000006068894,
      "bm": 0
    }
  ],
  "markers": []
}
