{
  "data": [
    {
      "properties": {
        "fi": {
          "name": "Suomensaaristokuljetus",
          "header": "Kauppatori - Vallisaari - Isosaari",
          "description": "Yhdistelmä lipulla käyt samana päivänä sekä Vallisaaressa että Isosaaressa",
          "free_text_1": "Vallisaari meno-paluu 10€ / 5€",
          "free_text_2": "Isosaari meno-paluu 18€ / 9€"
        },
        "en": {
          "name": "Suomensaaristokuljetus",
          "header": "Kauppatori - Vallisaari - Isosaari",
          "description": "Combination ticket allows you can visit both Vallisaari and Isosaari.",
          "free_text_1": "Vallisaari round-trip 10€ / 5€",
          "free_text_2": "Vallisaari round-trip 10€ / 5€"
        },
        "website": "http://www.suomensaaristokuljetus.fi/vallisaari-isosaari/",
        "phone_number": "0600 390 111",
        "type": "route",
        "tag": ["Kauppatori", "Vallisaari", "Isosaari"],
        "imageId": "7"
      }
    },
    {
      "properties": {
        "fi": {
          "name": "Aava Lines - Liuskasaari",
          "header": "Yhteysvene - Liuskasaari",
          "description": "Yhteysvene kulkee väliä HSS Manner - Liuskaluoto - Liuskasaari - Uunisaari - Kompassilaituri.",
          "free_text_1": "Liuskasaari 5€ / 3€",
          "free_text_2": "Uunisaari 4€ / 2,5€"
        },
        "en": {
          "name": "Aava Lines - Liuskasaari",
          "header": "Access boat - Liuskasaari",
          "description": "Access boat passes HSS Manner - Liuskaluoto - Liuskasaari - Uunisaari - Kompassilaituri.",
          "free_text_1": "Liuskasaari 5€ / 3€",
          "free_text_2": "Uunisaari 4€ / 2,5"
        },
        "website": "https://aavalines.fi",
        "phone_number": "040 6708845",
        "type": "route",
        "tag": [
          "HSS Manner",
          "Liuskaluoto",
          "Liuskasaari",
          "Uunisaari",
          "Kompassilaituri"
        ],
        "imageId": "7"
      }
    },
    {
      "properties": {
        "fi": {
          "name": "Suomen Saaristokuljetus Hakaniemi - Korkeasaari",
          "header": "Korkeasaareen ja takaisin lautalla",
          "description": "Suomen Saaristokuljetus Oy liikennöi kahdella linjalla Korkeasaaren eläintarhaan Kauppatorilta ja Hakaniemestä.",
          "free_text_1": "Meno-paluu 7 €",
          "free_text_2": "Alle 18-vuotiaat ilmaiseksi"
        },
        "en": {
          "name": "Suomen Saaristokuljetus Hakaniemi - Korkeasaari",
          "header": "To Korkeasaari and back by a ferry",
          "description": "Suomen Saaristokuljetus Oy operates two routes to the Korkeasaari Zoo. You can hop on from either the Market Square or Hakaniemi, and return to either.",
          "free_text_1": "Round-trip 7 €",
          "free_text_2": "Children under 18 free"
        },
        "website": "http://www.suomensaaristokuljetus.fi/korkeasaari/",
        "phone_number": "0600 390 111",
        "type": "route",
        "tag": ["Hakaniemi", "Korkeasaari"],
        "imageId": "7"
      }
    },
    {
      "properties": {
        "fi": {
          "name": "Suomen Saaristokuljetus Kauppatori - Korkeasaari",
          "header": "Korkeasaareen ja takaisin lautalla",
          "description": "Suomen Saaristokuljetus Oy liikennöi kahdella linjalla Korkeasaaren eläintarhaan Kauppatorilta ja Hakaniemestä.",
          "free_text_1": "Meno-paluu 7 €",
          "free_text_2": "Alle 18-vuotiaat ilmaiseksi"
        },
        "en": {
          "name": "<missing>",
          "header": "<To Korkeasaari and back by a ferry>",
          "description": "Suomen Saaristokuljetus Oy operates two routes to the Korkeasaari Zoo. You can hop on from either the Market Square or Hakaniemi, and return to either.",
          "free_text_1": "Round-trip 7 €",
          "free_text_2": "Children under 18 free"
        },
        "website": "http://www.suomensaaristokuljetus.fi/korkeasaari/",
        "phone_number": "0600 390 111",
        "type": "route",
        "tag": ["Kauppatori", "Korkeasaari"],
        "imageId": "7"
      }
    },
    {
      "properties": {
        "fi": {
          "name": "Suomen saaristokuljetus - Itäinen Saaristoreitti",
          "header": "Hakaniemestä aina Vuosaareen ja takaisin",
          "description": "Suomen Saaristokuljetus Oy liikennöi Helsingin upeinta saaristoreittiä Hakaniemen ja Vuosaaren välillä kesäkuun alusta aina elokuun loppuun saakka. Itäinen saaristoreitti on ainoa Helsingin kaupungin sisäinen vesiliikennereitti mantereelta mantereelle! Matkalla saat maistiaisen todellisesta helsinkiläisestä saaristolaiselämästä.\n\nRisteilyn kokonaiskesto on 1 h 45 minuuttia. Matkan aikana pääset tutustumaan niihin osiin Helsingin saaristoa, minne muut reitti- tai sightseeing-alukset eivät liikennöi. Reittiin sisältyy Degerön kanavan läpiajo.",
          "free_text_1": "Hinnat alkaen 5€",
          "free_text_2": "Polkupyörä 3€"
        },
        "en": {
          "name": "Suomen saaristokuljetus - Eastern archipelago route",
          "header": "From Hakaniemi to Vuosaari and back",
          "description": "<missing>",
          "free_text_1": "Price starts from 5€",
          "free_text_2": "Bicycle 3€"
        },
        "website": "http://www.suomensaaristokuljetus.fi/itainen-saaristoreitti/",
        "phone_number": "0600 390 111",
        "type": "route",
        "tag": [
          "Hakaniemi",
          "Herttoniemi",
          "Laajasalo",
          "Vartiosaari",
          "Kivisaari",
          "Satamasaari",
          "Iiluoto",
          "Leikonsaari",
          "Vuosaari"
        ],
        "imageId": "7"
      }
    },
    {
      "properties": {
        "fi": {
          "name": "JT-Line Hakaniemi - Vasikkasaari",
          "header": "Hakaniemi - Suomenlinna - Vallisaari - Vasikkasaari - Hakaniemi",
          "description": "Liikennöimme Hakaniemestä Suomenlinnan Tykistölahteen, Vallisaareen ja Vasikkasaareen joka päivä 29.6.-11.8.2019.",
          "free_text_1": "Meno-paluu 8€ / 4€",
          "free_text_2": "Island Hopping 10€ / 5€"
        },
        "en": {
          "name": "JT-Line Hakaniemi - Vasikkasaari",
          "header": "Hakaniemi - Suomenlinna - Vallisaari - Vasikkasaari - Hakaniemi",
          "description": "We ride from Hakaniemi to Suomenlinna, Vallisaari and Vasikkasaari every day from June 29th to August 11th, 2019",
          "free_text_1": "Round-trip 8€ / 4€",
          "free_text_2": "Island Hopping 10€ / 5€"
        },
        "website": "https://www.jt-line.fi/suomenlinna-vallisaari-lonna/aikataulu-hakaniemi-vasikkasaari/",
        "phone_number": "+358 10 2051880",
        "type": "route",
        "tag": ["Hakaneimi", "Suomenlinna", "Vallisaari", "Vasikkasaari"],
        "imageId": "7"
      }
    },
    {
      "properties": {
        "fi": {
          "name": "JT-Line Kauppatori - Suomenlinna",
          "header": "Kauppatori - Lonna - Vallisaari - Kauppatori",
          "description": "Matkan kesto Kauppatori-Tykistölahti on noin 25-40 minuuttia (riippuen siitä, pysähtyykö alus matkan aikana Lonnassa ja/tai Vallisaaressa). Matkan kesto Kauppatori-Kuninkaanportti on noin 30-45 minuuttia.",
          "free_text_1": "Meno-paluu 7€ / 3,50€",
          "free_text_2": "Island Hopping 10€ / 5€"
        },
        "en": {
          "name": "JT-Line Kauppatori - Suomenlinna",
          "header": "Kauppatori - Lonna - Vallisaari - Kauppatori",
          "description": "<missing>",
          "free_text_1": "Round-trip 7€ / 3,50€",
          "free_text_2": "Island Hopping 10€ / 5€"
        },
        "website": "https://www.jt-line.fi/suomenlinna-vallisaari-lonna/aikataulu-kauppatori-suomenlinna/",
        "phone_number": "+358 10 2051880",
        "type": "route",
        "tag": [
          "Kauppatori",
          "Lonna",
          "Suomenlinna",
          "Tykistölahti",
          "Kuninkaanportti"
        ],
        "imageId": "7"
      }
    },
    {
      "properties": {
        "fi": {
          "name": "HSL Lautta 19",
          "header": "Kauppatori - Suomenlinna AB lipulla",
          "description": "Suomenlinnan lauttaliikenteessä käyvät kaikki HSL:n matkaliput. Halvimmillaan Suomenlinnaan pääsee Helsingin sisäisen liikenteen kertalipulla. Kauppatorilla ja Katajanokalla on lippuautomaatti laiturialueella. Kertalippuja myydään lippuautomaattien lisäksi busseissa, raitiovaunuissa ja lähijunissa. Lippujen hinnoista ja kelpoisuudesta eri liikennevälineisiin saa tietoa HSL:n verkkosivuilta.",
          "free_text_1": "A vyöhyke",
          "free_text_2": "HSL lipulla merelle"
        },
        "en": {
          "name": "HSL Ferry 19",
          "header": "Kauppatori - Suomenlinna with AB ticket",
          "description": "<missing>",
          "free_text_1": "A zone",
          "free_text_2": "With HSL ticket to the sea"
        },
        "website": "https://reittiopas.hsl.fi/",
        "phone_number": "09 4766 4000",
        "type": "route",
        "tag": ["Kauppatori", "Suomenlinna"],
        "imageId": "7"
      }
    },
    {
      "properties": {
        "fi": {
          "name": "HSL Lautta 19E",
          "header": "Katajanokka - Suomenlinna AB lipulla",
          "description": "Suomenlinnan lauttaliikenteessä käyvät kaikki HSL:n matkaliput. Halvimmillaan Suomenlinnaan pääsee Helsingin sisäisen liikenteen kertalipulla. Kauppatorilla ja Katajanokalla on lippuautomaatti laiturialueella. Kertalippuja myydään lippuautomaattien lisäksi busseissa, raitiovaunuissa ja lähijunissa. Lippujen hinnoista ja kelpoisuudesta eri liikennevälineisiin saa tietoa HSL:n verkkosivuilta.",
          "free_text_1": "A vyöhyke",
          "free_text_2": "HSL lipulla merelle"
        },
        "en": {
          "name": "HSL Ferry 19E",
          "header": "Katajanokka - Suomenlinna with AB ticket",
          "description": "<missing>",
          "free_text_1": "A zone",
          "free_text_2": "<With HSL ticket to the sea>"
        },
        "website": "https://reittiopas.hsl.fi/",
        "phone_number": "09 4766 4000",
        "type": "route",
        "tag": [],
        "imageId": "7"
      }
    },
    {
      "properties": {
        "fi": {
          "name": "M/S Lotta Kauppatori - Jollas",
          "header": "Kauppatori - Kruunuvuorenranta - Vasikkasaari - Stansvik - Jollas - Kauppatori",
          "description": "City Cruisers on helsinkiläinen varustamo, jonka alus M/S Lotta on tilausristeily- ja reittiliikennekäytössä.",
          "free_text_1": "Meno-paluu 10€ / 5€",
          "free_text_2": "Polkupyörä 1,5€"
        },
        "en": {
          "name": "M/S Lotta Kauppatori - Jollas",
          "header": "Kauppatori - Kruunuvuorenranta - Vasikkasaari - Stansvik - Jollas - Kauppatori",
          "description": "<missing>",
          "free_text_1": "Round-trip 10€ / 5€",
          "free_text_2": "Bicycle 1,5€"
        },
        "website": "www.citycruisers.fi",
        "phone_number": "0400 216 795",
        "type": "route",
        "tag": [
          "Kauppatori",
          "Kruunuvuorenranta",
          "Vasikkasaari",
          "stansvik",
          "jollas"
        ],
        "imageId": "7"
      }
    },
    {
      "properties": {
        "fi": {
          "name": "Klippan - yhteysvene",
          "header": "Kahdessa minuutissa Saaristoon Klippanille",
          "description": "Ravintolalaskullenne lisätään automaattisesti yhteysvenemaksu 6,50/hlö (meno-paluu)\n\nSaariston laituri sijaitsee Olympiaterminaalin eteläpuolella (Ehrenströmintie), Rauhanpatsaan vieressä.\nUlkopuolisen yrittäjän, Oy Xmare Ab:n yhteysvene liikennöi Ravintola Saariston aukioloaikoina 20 minuutin. Lyhyt merimatka kestää vain pari minuuttia.",
          "free_text_1": "Meno-paluu 6,50€",
          "free_text_2": "20 minuutin välein"
        },
        "en": {
          "name": "Klippan - access boat",
          "header": "Two minutes to restaurant Saaristo at Klippan",
          "description": "Restaurant Saaristo is located on Island Klippan, on the south side of Olympia-terminal.\nA boat serves from pier  located on the south side of Olympia-terminal, by the street Ehrenströmintie (next to the Peace Statue).",
          "free_text_1": "Round-trip 6,50€",
          "free_text_2": "Every 20 minutes"
        },
        "website": "https://www.ravintolasaaristo.fi",
        "phone_number": "+358 9 7425 5590",
        "type": "route",
        "tag": ["Klippan", "luoto"],
        "imageId": "7"
      }
    },
    {
      "properties": {
        "fi": {
          "name": "NJK vierassatama yhteysalus",
          "header": "Yhteysalus Valkosaari / Ravintola NJK",
          "description": "Yhteysalus Valkosaareen",
          "free_text_1": "Lauttamaksu 7,20€",
          "free_text_2": "Yhteys Klippanin luodolle"
        },
        "en": {
          "name": "NJK guest harbour access vessel",
          "header": "Access vessel to Valkosaari / Restaurant NJK",
          "description": "Access vessel to Valkosaari",
          "free_text_1": "The ferry fee 7,20€",
          "free_text_2": "Access to Klippan Island"
        },
        "website": "http://www.njk.fi/vierassatama/",
        "phone_number": "+358 9 636 047",
        "type": "route",
        "tag": ["Valkosaari"],
        "imageId": "7"
      }
    },
    {
      "properties": {
        "fi": {
          "name": "JT-Line Merisatama - Pihlajasaari",
          "header": "Vesibussi Merisatama - Pihlajasaari",
          "description": "Lähdöt Kaivopuiston Merisatamasta: Merisatamanranta 10. Lippuja voi ostaa joko verkkokaupastamme tai suoraan aluksesta.",
          "free_text_1": "Meno-paluu 7,50€ / 4,50€",
          "free_text_2": "Saatavilla sarjalippu 10-matkaa"
        },
        "en": {
          "name": "JT-Line Merisatama - Pihlajasaari",
          "header": "Water bus Merisatama - Pihlajasaari",
          "description": "Departures from Kaivopuisto Merisatama: Merisatamanranta 10. Tickets can be purchased either online or directly from the ship.",
          "free_text_1": "Round-trip 7,50€ / 4,50€",
          "free_text_2": "10 trips Season tickets available"
        },
        "website": "https://www.jt-line.fi/pihlajasaari/",
        "phone_number": "+358 10 2051880",
        "type": "route",
        "tag": ["<Merisatama", "Pihlajasaari"],
        "imageId": "7"
      }
    },
    {
      "properties": {
        "fi": {
          "name": "JT-Line Ruoholahti - Pihlajasaari",
          "header": "Vesibussi Ruoholahti - Pihlajasaari",
          "description": "Lähdöt Ruoholahdesta: Kellosaarenranta 1. Lippuja voi ostaa joko verkkokaupastamme tai suoraan aluksesta.",
          "free_text_1": "Meno-paluu 7,50€ / 4,50€",
          "free_text_2": "10 trips Season tickets available"
        },
        "en": {
          "name": "JT-Line Ruoholahti - Pihlajasaari",
          "header": "Water bus Ruoholahti - Pihlajasaari",
          "description": "Departures from Ruoholahti: Kellosaarenranta 1. Tickets can be purchased either online or directly from the ship.",
          "free_text_1": "Round-trip 7,50€ / 4,50€",
          "free_text_2": "10 trips Season tickets available"
        },
        "website": "https://www.jt-line.fi/pihlajasaari/",
        "phone_number": "+358 10 2051880",
        "type": "route",
        "tag": ["Ruoholahti", "Pihlajasaari"],
        "imageId": "7"
      }
    },
    {
      "properties": {
        "fi": {
          "name": "Ferra - Sirpalesaari",
          "header": "Yhteysalus Sirpalesaareen",
          "description": "Yhteysalus lähtee Sirpalesaaresta aikataulun mukaisesti. Matka kestää noin 2 minuuttia. Alus pysähtyy Merisatamaan hakemaan matkustajat, ja palaa Sirpalesaareen välittömästi.",
          "free_text_1": "Meno-paluu 6€ / 3€",
          "free_text_2": "Merisatamanranta 10"
        },
        "en": {
          "name": "Ferra - Sirpalesaari",
          "header": "Access vessel to Sirpalesaari island",
          "description": "The access vessel departs from Sirpalesaari on schedule. The journey takes about 2 minutes. The ship stops at Merisatama to pick up passengers and returns to Sirpalesaari immediately.",
          "free_text_1": "Round-trip 6€ / 3€",
          "free_text_2": "Merisatamanranta 10"
        },
        "website": "https://www.ferra.fi",
        "phone_number": "+358-408279264",
        "type": "route",
        "tag": ["Sirpalesaari", "Ravintola Saari", "Merisatama"],
        "imageId": "7"
      }
    },
    {
      "properties": {
        "fi": {
          "name": "Norsöline - Kaunissaari",
          "header": "Vuosaari - Kaunissaari",
          "description": "Kuljetamme teidät Sipoon Kaunissaareen. Kaunissaari sijaitsee 10km päässä Vuosaaresta itään, avomeren laidalla. Saaresta on telttailu- ja mökkimajoitus, uimarantoja, ravintola, saunoja, keittokatoksia ja jätehuolto.",
          "free_text_1": "Meno-paluu 22€ / 10€",
          "free_text_2": "Kalkkihiekantori, Vuosaari"
        },
        "en": {
          "name": "Norsöline - Kaunissaari",
          "header": "Vuosaari - Kaunissaari",
          "description": "NorsöLine takes you to one of the most beautiful islands in the archipelago of Sipoo. The name Kaunissaari means Beautiful Island, and that it truly is with all its beautiful nature and amazing sea views! On the island you will find a restaurant, several places to barbeque, saunas and a lot of amazing beaches. If you wish to spend the night on the island you can choose from camping or renting a cabin. So come and spend a wonderful summer day in Kaunissaari alone or with your friends, family or colleagues.",
          "free_text_1": "Round-trip 22€ / 10€",
          "free_text_2": "Kalkkihiekantori, Vuosaari"
        },
        "website": "https://norsoline.com",
        "phone_number": "0500 - 821 921",
        "type": "route",
        "tag": ["Vuosaari", "Kaunissaari"],
        "imageId": "7"
      }
    },
    {
      "properties": {
        "fi": {
          "name": "Merenkävijät - Särkkä - Harakka",
          "header": "Yhteysalus - Ullanlinnanlaituri - Särkkä - Harakansaari",
          "description": "Kutsu vene nostamalla merkkiviitta ylös myös silloin, kun vene on laiturissa. Vene lähtee sieltä, mihin on viimeksi jättänyt matkustajia, ja ajaa tarvittavat välit.",
          "free_text_1": "Särkkä - meno-paluu 7,50€",
          "free_text_2": "Harakka - meno-paluu 7,50€"
        },
        "en": {
          "name": "Merenkävijät - Särkkä - Harakka",
          "header": "Access vessel - Ullanlinnanlaituri - Särkkä - Harakansaari",
          "description": "Call the boat by lifting the wooden call sign. The boat leaves every 20/30 minutes from Kaivopuisto/Harakka/Särkkä depending on where it has last left passengers. All required crossings will be covered when the boat is moving.​",
          "free_text_1": "Särkkä - round-trip 7,50€",
          "free_text_2": "Harakka - round-trip 5€"
        },
        "website": "http://www.merenkavijat.fi/yhteysveneen-aikataulut.html",
        "phone_number": "+358 40 533 9536",
        "type": "route",
        "tag": [
          "Ullanlinnanlaituri",
          "Harakansaari",
          "harakka",
          "Särkänsaari",
          "särkkä"
        ],
        "imageId": "7"
      }
    },
    {
      "properties": {
        "fi": {
          "name": "Mustasaaren Lautta",
          "header": "Yhteyslautta Töölöstä Mustasaareen",
          "description": "Mustasaareen pääsee lautalla. Taivallahden laituri sijaitsee Töölössä Eteläisen Hesperiankadun pään lähellä. Lauttamatka kestää noin 15 minuuttia. Lauttaan mahtuu kerrallaan enintään 98 matkustajaa. Lautan kansi on esteetön, ja sinne pääsee lastenvaunuilla ja pyörätuolilla.",
          "free_text_1": "Meno-paluu 4€",
          "free_text_2": "Hiekkarannantie 5"
        },
        "en": {
          "name": "Ferry - Mustasaari",
          "header": "Ferry from Töölö to Mustasaari",
          "description": "The island is accessible via ferry from Taivallahti from the beginning of June until the middle of August (4.6. - 11.8.) The Taivallahti wharf is located at the end of Eteläinen Hesperiankatu. The exact address is Hiekkarannantie 5. It is advisable to use public transport when travelling to Taivallahti, since there is very limited parking space available. The ferry ride takes circa 15 minutes, during which you can enjoy the refreshing coastal air and scenery. The adult fare for return tickets is 4 euros and children under the age of 10 travel free. Remember that the fares are paid with cash. The ferry is accessible for persons with disabilities.",
          "free_text_1": "Round-trip 4€",
          "free_text_2": "Hiekkarannantie 5"
        },
        "website": "https://www.mustasaarentoimintakeskus.fi/index/saapuminen.html#lauttaliikenne",
        "phone_number": "mustasaari@evl.fi",
        "type": "route",
        "tag": [],
        "imageId": "7"
      }
    }
  ]
}
